{
  "drgnfld": [
    {
      "template": "1434",
      "type": "1",
      "x": "-117.546875",
      "z": "-7.078125",
      "y": "69.5",
      "roll": "0",
      "pitch": "0",
      "turn": "0",
      "id": "noname",
      "script": "flag"
    },
    {
      "template": "1434",
      "type": "1",
      "x": "-124.5",
      "z": "0.578125",
      "y": "21.5",
      "roll": "0",
      "pitch": "0",
      "turn": "0",
      "id": "noname",
      "script": "flag"
    },
    {
      "template": "1434",
      "type": "1",
      "x": "-124.5",
      "z": "0.578125",
      "y": "38.5",
      "roll": "0",
      "pitch": "0",
      "turn": "0",
      "id": "noname",
      "script": "flag"
    },
    {
      "template": "1434",
      "type": "1",
      "x": "-124.5",
      "z": "0.578125",
      "y": "89.5",
      "roll": "0",
      "pitch": "0",
      "turn": "0",
      "id": "noname",
      "script": "flag"
    },
    {
      "template": "1434",
      "type": "1",
      "x": "-124.5",
      "z": "0.578125",
      "y": "106.5",
      "roll": "0",
      "pitch": "0",
      "turn": "0",
      "id": "noname",
      "script": "flag"
    },
    {
      "template": "1433",
      "type": "1",
      "x": "-80.890625",
      "z": "-11.1953125",
      "y": "7.6953125",
      "roll": "0",
      "pitch": "0",
      "turn": "65",
      "id": "noname",
      "script": "raiderroof"
    },
    {
      "template": "317",
      "type": "8",
      "x": "-28.625",
      "z": "-9.265625",
      "y": "113.734375",
      "roll": "0",
      "pitch": "0",
      "turn": "-60",
      "id": "noname",
      "script": "drgnfld\\loot1.s"
    },
    {
      "template": "317",
      "type": "8",
      "x": "-21.5",
      "z": "-7.375",
      "y": "113.71875",
      "roll": "0",
      "pitch": "0",
      "turn": "-60",
      "id": "noname",
      "script": "drgnfld\\loot2.s"
    },
    {
      "template": "4003",
      "type": "2",
      "x": "-32.5",
      "z": "-8.125",
      "y": "78.890625",
      "roll": "0",
      "pitch": "0",
      "turn": "-60",
      "id": "noname",
      "script": "monsters\\shardwolf.s"
    },
    {
      "template": "4003",
      "type": "2",
      "x": "-32.5",
      "z": "-8.125",
      "y": "80.890625",
      "roll": "0",
      "pitch": "0",
      "turn": "-60",
      "id": "noname",
      "script": "monsters\\shardwolf.s"
    },
    {
      "template": "316",
      "type": "8",
      "x": "-34.453125",
      "z": "-7.609375",
      "y": "79.5",
      "roll": "5",
      "pitch": "0",
      "turn": "50",
      "id": "Bones",
      "script": "drgnfld\\rt_c.s"
    },
    {
      "template": "118",
      "type": "2",
      "x": "-94.5",
      "z": "-9.5",
      "y": "37.5",
      "roll": "0",
      "pitch": "0",
      "turn": "0",
      "id": "noname",
      "script": "monsters\\Bandit_Mage.s"
    },
    {
      "template": "4003",
      "type": "2",
      "x": "-99.5",
      "z": "-9.5",
      "y": "38.5",
      "roll": "0",
      "pitch": "0",
      "turn": "0",
      "id": "noname",
      "script": "monsters\\shardwolf.s"
    },
    {
      "template": "4003",
      "type": "2",
      "x": "-97.5",
      "z": "-9.5",
      "y": "34.5",
      "roll": "0",
      "pitch": "0",
      "turn": "0",
      "id": "noname",
      "script": "monsters\\shardwolf.s"
    },
    {
      "template": "4003",
      "type": "2",
      "x": "-8.5",
      "z": "-9.375",
      "y": "69.5",
      "roll": "0",
      "pitch": "0",
      "turn": "0",
      "id": "noname",
      "script": "monsters\\shardwolf.s"
    },
    {
      "template": "254",
      "type": "2",
      "x": "-10.5",
      "z": "-8.875",
      "y": "59.5",
      "roll": "0",
      "pitch": "0",
      "turn": "0",
      "id": "noname",
      "script": "monsters\\Nubbed_Wormmouth.s"
    },
    {
      "template": "254",
      "type": "2",
      "x": "-7.5",
      "z": "-8.75",
      "y": "58.5",
      "roll": "0",
      "pitch": "0",
      "turn": "0",
      "id": "noname",
      "script": "monsters\\Nubbed_Wormmouth.s"
    },
    {
      "template": "118",
      "type": "2",
      "x": "-78.5",
      "z": "-9.5",
      "y": "51.5",
      "roll": "0",
      "pitch": "0",
      "turn": "0",
      "id": "noname",
      "script": "monsters\\Bandit_Mage.s"
    },
    {
      "template": "4207",
      "type": "2",
      "x": "-76.5",
      "z": "-9.5",
      "y": "48.5",
      "roll": "0",
      "pitch": "0",
      "turn": "0",
      "id": "noname",
      "script": "monsters\\raider.s"
    },
    {
      "template": "301",
      "type": "8",
      "x": "-73.6328125",
      "z": "-11.8125",
      "y": "11.875",
      "roll": "0",
      "pitch": "0",
      "turn": "-80",
      "id": "noname",
      "script": "drgnfld\\rt_b.s"
    },
    {
      "template": "107",
      "type": "2",
      "x": "-72.984375",
      "z": "-10.33984375",
      "y": "15.765625",
      "roll": "0",
      "pitch": "0",
      "turn": "-1",
      "id": "noname",
      "script": "monsters\\Bandit_Thug.s"
    },
    {
      "template": "4207",
      "type": "2",
      "x": "-79.5",
      "z": "-10.4375",
      "y": "16.5",
      "roll": "0",
      "pitch": "0",
      "turn": "0",
      "id": "noname",
      "script": "monsters\\raider.s"
    },
    {
      "template": "118",
      "type": "2",
      "x": "-75.5",
      "z": "-11.625",
      "y": "13.5",
      "roll": "0",
      "pitch": "0",
      "turn": "0",
      "id": "noname",
      "script": "monsters\\Bandit_Mage.s"
    },
    {
      "template": "254",
      "type": "2",
      "x": "-115.5",
      "z": "-9.5",
      "y": "22.5",
      "roll": "0",
      "pitch": "0",
      "turn": "0",
      "id": "noname",
      "script": "monsters\\Nubbed_Wormmouth.s"
    },
    {
      "template": "254",
      "type": "2",
      "x": "-116.5",
      "z": "-9.5",
      "y": "24.5",
      "roll": "0",
      "pitch": "0",
      "turn": "0",
      "id": "noname",
      "script": "monsters\\Nubbed_Wormmouth.s"
    },
    {
      "template": "207",
      "type": "2",
      "x": "-108.5",
      "z": "-9.125",
      "y": "23.5",
      "roll": "0",
      "pitch": "0",
      "turn": "0",
      "id": "noname",
      "script": "monsters\\Ace_Archer.s"
    },
    {
      "template": "207",
      "type": "2",
      "x": "-93.09375",
      "z": "-8.69921875",
      "y": "73.921875",
      "roll": "0",
      "pitch": "0",
      "turn": "0",
      "id": "noname",
      "script": "drgnfld\\Ace_Archer_Q31.s"
    },
    {
      "template": "207",
      "type": "2",
      "x": "-48.5",
      "z": "-9.5",
      "y": "39.5",
      "roll": "0",
      "pitch": "0",
      "turn": "0",
      "id": "noname",
      "script": "monsters\\Ace_Archer.s"
    },
    {
      "template": "107",
      "type": "2",
      "x": "-49.5",
      "z": "-9.5",
      "y": "37.5",
      "roll": "0",
      "pitch": "0",
      "turn": "0",
      "id": "noname",
      "script": "monsters\\Bandit_Thug.s"
    },
    {
      "template": "107",
      "type": "2",
      "x": "-50.5",
      "z": "-9.5",
      "y": "40.5",
      "roll": "0",
      "pitch": "0",
      "turn": "1",
      "id": "noname",
      "script": "monsters\\Bandit_Thug.s"
    },
    {
      "template": "254",
      "type": "2",
      "x": "-16.5",
      "z": "-9.5",
      "y": "86.5",
      "roll": "0",
      "pitch": "0",
      "turn": "0",
      "id": "noname",
      "script": "monsters\\Nubbed_Wormmouth.s"
    },
    {
      "template": "254",
      "type": "2",
      "x": "-13.5",
      "z": "-9.4375",
      "y": "91.5",
      "roll": "0",
      "pitch": "0",
      "turn": "-1",
      "id": "noname",
      "script": "monsters\\Nubbed_Wormmouth.s"
    },
    {
      "template": "254",
      "type": "2",
      "x": "-21.5",
      "z": "-9.5",
      "y": "89.5",
      "roll": "0",
      "pitch": "0",
      "turn": "0",
      "id": "noname",
      "script": "monsters\\Nubbed_Wormmouth.s"
    },
    {
      "template": "252",
      "type": "2",
      "x": "-114.5",
      "z": "-9.125",
      "y": "114.5",
      "roll": "0",
      "pitch": "0",
      "turn": "0",
      "id": "noname",
      "script": "monsters\\Horrid_Wormmouth.s"
    },
    {
      "template": "118",
      "type": "2",
      "x": "-87.671875",
      "z": "-3.4375",
      "y": "79.5",
      "roll": "0",
      "pitch": "0",
      "turn": "0",
      "id": "noname",
      "script": "drgnfld\\Bandit_Mage_Q31.s"
    },
    {
      "template": "118",
      "type": "2",
      "x": "-96.671875",
      "z": "-8.12890625",
      "y": "83.5",
      "roll": "0",
      "pitch": "0",
      "turn": "0",
      "id": "noname",
      "script": "drgnfld\\Bandit_Mage_Q31.s"
    },
    {
      "template": "207",
      "type": "2",
      "x": "-90.765625",
      "z": "-3.09765625",
      "y": "82.546875",
      "roll": "0",
      "pitch": "0",
      "turn": "0",
      "id": "noname",
      "script": "drgnfld\\Ace_Archer_Q31.s"
    },
    {
      "template": "207",
      "type": "2",
      "x": "-85.328125",
      "z": "-3",
      "y": "83.5",
      "roll": "0",
      "pitch": "0",
      "turn": "0",
      "id": "noname",
      "script": "drgnfld\\Ace_Archer_Q31.s"
    },
    {
      "template": "4207",
      "type": "2",
      "x": "-85.421875",
      "z": "-8.4140625",
      "y": "73.9375",
      "roll": "0",
      "pitch": "0",
      "turn": "0",
      "id": "noname",
      "script": "drgnfld\\raider_Q31.s"
    },
    {
      "template": "4207",
      "type": "2",
      "x": "-91.375",
      "z": "-5.94140625",
      "y": "88.28125",
      "roll": "0",
      "pitch": "0",
      "turn": "0",
      "id": "noname",
      "script": "drgnfld\\raider_Q31.s"
    },
    {
      "template": "4207",
      "type": "2",
      "x": "-81.375",
      "z": "-6.203125",
      "y": "87.671875",
      "roll": "0",
      "pitch": "0",
      "turn": "0",
      "id": "noname",
      "script": "drgnfld\\raider_Q31.s"
    },
    {
      "template": "107",
      "type": "2",
      "x": "-94.5",
      "z": "-6.140625",
      "y": "79.890625",
      "roll": "0",
      "pitch": "0",
      "turn": "0",
      "id": "noname",
      "script": "drgnfld\\Bandit_Thug_Q31.s"
    },
    {
      "template": "107",
      "type": "2",
      "x": "-80.203125",
      "z": "-6.59765625",
      "y": "79.5",
      "roll": "0",
      "pitch": "0",
      "turn": "0",
      "id": "noname",
      "script": "drgnfld\\Bandit_Thug_Q31.s"
    },
    {
      "template": "292",
      "type": "2",
      "x": "-119.5",
      "z": "-9.5",
      "y": "63.2890625",
      "roll": "0",
      "pitch": "0",
      "turn": "-52",
      "id": "noname",
      "script": "monsters\\Teresa.s"
    },
    {
      "template": "1018",
      "type": "1",
      "x": "-109.109375",
      "z": "-7.5390625",
      "y": "112.71875",
      "roll": "0",
      "pitch": "0",
      "turn": "-40",
      "id": "noname",
      "script": "DFtree2\\Teresa.s"
    },
    {
      "template": "1018",
      "type": "1",
      "x": "-106.5",
      "z": "-7.9296875",
      "y": "113.5",
      "roll": "0",
      "pitch": "0",
      "turn": "-65",
      "id": "noname",
      "script": "DFtree2\\Teresa.s"
    },
    {
      "template": "1018",
      "type": "1",
      "x": "-103.5",
      "z": "-7.9296875",
      "y": "113.5",
      "roll": "0",
      "pitch": "0",
      "turn": "-65",
      "id": "noname",
      "script": "DFtree2\\Teresa.s"
    },
    {
      "template": "1018",
      "type": "1",
      "x": "-100.5",
      "z": "-7.9296875",
      "y": "113.5",
      "roll": "0",
      "pitch": "0",
      "turn": "-65",
      "id": "noname",
      "script": "DFtree2\\Teresa.s"
    },
    {
      "template": "1018",
      "type": "1",
      "x": "-97.5",
      "z": "-7.9296875",
      "y": "113.5",
      "roll": "0",
      "pitch": "0",
      "turn": "-65",
      "id": "noname",
      "script": "DFtree2\\Teresa.s"
    },
    {
      "template": "1018",
      "type": "1",
      "x": "-94.5",
      "z": "-7.9296875",
      "y": "113.5",
      "roll": "0",
      "pitch": "0",
      "turn": "-65",
      "id": "noname",
      "script": "DFtree2\\Teresa.s"
    },
    {
      "template": "1018",
      "type": "1",
      "x": "-91.5",
      "z": "-7.9296875",
      "y": "113.5",
      "roll": "0",
      "pitch": "0",
      "turn": "-65",
      "id": "noname",
      "script": "DFtree2\\Teresa.s"
    },
    {
      "template": "1018",
      "type": "1",
      "x": "-88.5",
      "z": "-7.9296875",
      "y": "113.5",
      "roll": "0",
      "pitch": "0",
      "turn": "-65",
      "id": "noname",
      "script": "DFtree2\\Teresa.s"
    },
    {
      "template": "1018",
      "type": "1",
      "x": "-56.5",
      "z": "-8.4375",
      "y": "124.890625",
      "roll": "0",
      "pitch": "0",
      "turn": "60",
      "id": "noname",
      "script": "DFtree2\\Teresa.s"
    },
    {
      "template": "1018",
      "type": "1",
      "x": "-59.5",
      "z": "-8.4375",
      "y": "124.890625",
      "roll": "0",
      "pitch": "0",
      "turn": "60",
      "id": "noname",
      "script": "DFtree2\\Teresa.s"
    },
    {
      "template": "1018",
      "type": "1",
      "x": "-120.5",
      "z": "-8.4375",
      "y": "124.890625",
      "roll": "0",
      "pitch": "0",
      "turn": "60",
      "id": "noname",
      "script": "DFtree2\\Teresa.s"
    },
    {
      "template": "1018",
      "type": "1",
      "x": "-117.5",
      "z": "-8.4375",
      "y": "124.890625",
      "roll": "0",
      "pitch": "0",
      "turn": "60",
      "id": "noname",
      "script": "DFtree2\\Teresa.s"
    },
    {
      "template": "1018",
      "type": "1",
      "x": "-114.5",
      "z": "-8.4375",
      "y": "124.890625",
      "roll": "0",
      "pitch": "0",
      "turn": "60",
      "id": "noname",
      "script": "DFtree2\\Teresa.s"
    },
    {
      "template": "1018",
      "type": "1",
      "x": "-111.5",
      "z": "-8.4375",
      "y": "124.890625",
      "roll": "0",
      "pitch": "0",
      "turn": "60",
      "id": "noname",
      "script": "DFtree2\\Teresa.s"
    },
    {
      "template": "1018",
      "type": "1",
      "x": "-108.5",
      "z": "-8.4375",
      "y": "124.890625",
      "roll": "0",
      "pitch": "0",
      "turn": "60",
      "id": "noname",
      "script": "DFtree2\\Teresa.s"
    },
    {
      "template": "1018",
      "type": "1",
      "x": "-105.5",
      "z": "-8.4375",
      "y": "124.890625",
      "roll": "0",
      "pitch": "0",
      "turn": "60",
      "id": "noname",
      "script": "DFtree2\\Teresa.s"
    },
    {
      "template": "1018",
      "type": "1",
      "x": "-102.5",
      "z": "-8.4375",
      "y": "124.890625",
      "roll": "0",
      "pitch": "0",
      "turn": "60",
      "id": "noname",
      "script": "DFtree2\\Teresa.s"
    },
    {
      "template": "1018",
      "type": "1",
      "x": "-99.5",
      "z": "-8.4375",
      "y": "124.890625",
      "roll": "0",
      "pitch": "0",
      "turn": "60",
      "id": "noname",
      "script": "DFtree2\\Teresa.s"
    },
    {
      "template": "1018",
      "type": "1",
      "x": "-96.5",
      "z": "-8.4375",
      "y": "124.890625",
      "roll": "0",
      "pitch": "0",
      "turn": "60",
      "id": "noname",
      "script": "DFtree2\\Teresa.s"
    },
    {
      "template": "1018",
      "type": "1",
      "x": "-93.5",
      "z": "-8.4375",
      "y": "124.890625",
      "roll": "0",
      "pitch": "0",
      "turn": "60",
      "id": "noname",
      "script": "DFtree2\\Teresa.s"
    },
    {
      "template": "1018",
      "type": "1",
      "x": "-90.5",
      "z": "-8.4375",
      "y": "124.890625",
      "roll": "0",
      "pitch": "0",
      "turn": "60",
      "id": "noname",
      "script": "DFtree2\\Teresa.s"
    },
    {
      "template": "1018",
      "type": "1",
      "x": "-87.5",
      "z": "-8.4375",
      "y": "124.890625",
      "roll": "0",
      "pitch": "0",
      "turn": "60",
      "id": "noname",
      "script": "DFtree2\\Teresa.s"
    },
    {
      "template": "1018",
      "type": "1",
      "x": "-84.5",
      "z": "-8.4375",
      "y": "124.890625",
      "roll": "0",
      "pitch": "0",
      "turn": "60",
      "id": "noname",
      "script": "DFtree2\\Teresa.s"
    },
    {
      "template": "1018",
      "type": "1",
      "x": "-81.5",
      "z": "-8.4375",
      "y": "124.890625",
      "roll": "0",
      "pitch": "0",
      "turn": "60",
      "id": "noname",
      "script": "DFtree2\\Teresa.s"
    },
    {
      "template": "1018",
      "type": "1",
      "x": "-69.5",
      "z": "-8.4375",
      "y": "124.890625",
      "roll": "0",
      "pitch": "0",
      "turn": "60",
      "id": "noname",
      "script": "DFtree2\\Teresa.s"
    },
    {
      "template": "1018",
      "type": "1",
      "x": "-72.5",
      "z": "-8.4375",
      "y": "124.890625",
      "roll": "0",
      "pitch": "0",
      "turn": "60",
      "id": "noname",
      "script": "DFtree2\\Teresa.s"
    },
    {
      "template": "1018",
      "type": "1",
      "x": "-76.5",
      "z": "-8.4375",
      "y": "124.890625",
      "roll": "0",
      "pitch": "0",
      "turn": "60",
      "id": "noname",
      "script": "DFtree2\\Teresa.s"
    },
    {
      "template": "7",
      "type": "1",
      "x": "-38.5",
      "z": "-9.609375",
      "y": "118.5",
      "roll": "0",
      "pitch": "0",
      "turn": "0",
      "id": "noname",
      "script": "pinetreeTeresa.s"
    },
    {
      "template": "7",
      "type": "1",
      "x": "-60.5",
      "z": "-9.609375",
      "y": "109.5",
      "roll": "0",
      "pitch": "0",
      "turn": "0",
      "id": "noname",
      "script": "pinetreeTeresa.s"
    },
    {
      "template": "7",
      "type": "1",
      "x": "-82.5",
      "z": "-9.609375",
      "y": "107.5",
      "roll": "0",
      "pitch": "0",
      "turn": "0",
      "id": "noname",
      "script": "pinetreeTeresa.s"
    },
    {
      "template": "7",
      "type": "1",
      "x": "-88.5",
      "z": "-9.609375",
      "y": "98.5",
      "roll": "0",
      "pitch": "0",
      "turn": "0",
      "id": "noname",
      "script": "pinetreeTeresa.s"
    },
    {
      "template": "7",
      "type": "1",
      "x": "-100.5",
      "z": "-9.609375",
      "y": "95.5",
      "roll": "0",
      "pitch": "0",
      "turn": "0",
      "id": "noname",
      "script": "pinetreeTeresa.s"
    },
    {
      "template": "7",
      "type": "1",
      "x": "-111.5",
      "z": "-9.609375",
      "y": "76.5",
      "roll": "0",
      "pitch": "0",
      "turn": "0",
      "id": "noname",
      "script": "pinetreeTeresa.s"
    },
    {
      "template": "7",
      "type": "1",
      "x": "-92.5",
      "z": "-9.609375",
      "y": "69.5",
      "roll": "0",
      "pitch": "0",
      "turn": "0",
      "id": "noname",
      "script": "pinetreeTeresa.s"
    },
    {
      "template": "7",
      "type": "1",
      "x": "-97.5",
      "z": "-9.609375",
      "y": "56.5",
      "roll": "0",
      "pitch": "0",
      "turn": "0",
      "id": "noname",
      "script": "pinetreeTeresa.s"
    },
    {
      "template": "7",
      "type": "1",
      "x": "-114.5",
      "z": "-9.609375",
      "y": "47.5",
      "roll": "0",
      "pitch": "0",
      "turn": "0",
      "id": "noname",
      "script": "pinetreeTeresa.s"
    },
    {
      "template": "7",
      "type": "1",
      "x": "-117.5",
      "z": "-9.609375",
      "y": "12.5",
      "roll": "0",
      "pitch": "0",
      "turn": "0",
      "id": "noname",
      "script": "pinetreeTeresa.s"
    },
    {
      "template": "7",
      "type": "1",
      "x": "-80.5",
      "z": "-9.609375",
      "y": "23.5",
      "roll": "0",
      "pitch": "0",
      "turn": "0",
      "id": "noname",
      "script": "pinetreeTeresa.s"
    },
    {
      "template": "7",
      "type": "1",
      "x": "-74.5",
      "z": "-9.609375",
      "y": "20.5",
      "roll": "0",
      "pitch": "0",
      "turn": "0",
      "id": "noname",
      "script": "pinetreeTeresa.s"
    },
    {
      "template": "7",
      "type": "1",
      "x": "-113.5",
      "z": "-9.609375",
      "y": "30.5",
      "roll": "0",
      "pitch": "0",
      "turn": "0",
      "id": "noname",
      "script": "pinetreeTeresa.s"
    },
    {
      "template": "7",
      "type": "1",
      "x": "-71.5",
      "z": "-11.953125",
      "y": "11.5",
      "roll": "0",
      "pitch": "0",
      "turn": "0",
      "id": "noname",
      "script": "pinetreeTeresa.s"
    },
    {
      "template": "7",
      "type": "1",
      "x": "-92.5",
      "z": "-11.171875",
      "y": "15.5",
      "roll": "0",
      "pitch": "0",
      "turn": "0",
      "id": "noname",
      "script": "pinetreeTeresa.s"
    },
    {
      "template": "7",
      "type": "1",
      "x": "-99.5",
      "z": "-10.78125",
      "y": "10.5",
      "roll": "0",
      "pitch": "0",
      "turn": "0",
      "id": "noname",
      "script": "pinetreeTeresa.s"
    },
    {
      "template": "7",
      "type": "1",
      "x": "-24.5",
      "z": "-9.609375",
      "y": "18.5",
      "roll": "0",
      "pitch": "0",
      "turn": "0",
      "id": "noname",
      "script": "pinetreeTeresa.s"
    },
    {
      "template": "7",
      "type": "1",
      "x": "-17.5",
      "z": "-10.78125",
      "y": "9.5",
      "roll": "0",
      "pitch": "0",
      "turn": "0",
      "id": "noname",
      "script": "pinetreeTeresa.s"
    },
    {
      "template": "7",
      "type": "1",
      "x": "-52.5",
      "z": "-9.609375",
      "y": "10.5",
      "roll": "0",
      "pitch": "0",
      "turn": "0",
      "id": "noname",
      "script": "pinetreeTeresa.s"
    },
    {
      "template": "7",
      "type": "1",
      "x": "-52.5",
      "z": "-9.609375",
      "y": "24.5",
      "roll": "0",
      "pitch": "0",
      "turn": "0",
      "id": "noname",
      "script": "pinetreeTeresa.s"
    },
    {
      "template": "7",
      "type": "1",
      "x": "-51.5",
      "z": "-9.609375",
      "y": "34.5",
      "roll": "0",
      "pitch": "0",
      "turn": "0",
      "id": "noname",
      "script": "pinetreeTeresa.s"
    },
    {
      "template": "7",
      "type": "1",
      "x": "-47.5",
      "z": "-9.609375",
      "y": "26.5",
      "roll": "0",
      "pitch": "0",
      "turn": "0",
      "id": "noname",
      "script": "pinetreeTeresa.s"
    },
    {
      "template": "7",
      "type": "1",
      "x": "-89.5",
      "z": "-9.609375",
      "y": "37.5",
      "roll": "0",
      "pitch": "0",
      "turn": "0",
      "id": "noname",
      "script": "pinetreeTeresa.s"
    },
    {
      "template": "7",
      "type": "1",
      "x": "-76.5",
      "z": "-9.609375",
      "y": "38.5",
      "roll": "0",
      "pitch": "0",
      "turn": "0",
      "id": "noname",
      "script": "pinetreeTeresa.s"
    },
    {
      "template": "7",
      "type": "1",
      "x": "-78.5",
      "z": "-9.609375",
      "y": "43.5",
      "roll": "0",
      "pitch": "0",
      "turn": "0",
      "id": "noname",
      "script": "pinetreeTeresa.s"
    },
    {
      "template": "7",
      "type": "1",
      "x": "-73.5",
      "z": "-9.609375",
      "y": "53.5",
      "roll": "0",
      "pitch": "0",
      "turn": "0",
      "id": "noname",
      "script": "pinetreeTeresa.s"
    },
    {
      "template": "7",
      "type": "1",
      "x": "-67.5",
      "z": "-9.609375",
      "y": "67.5",
      "roll": "0",
      "pitch": "0",
      "turn": "0",
      "id": "noname",
      "script": "pinetreeTeresa.s"
    },
    {
      "template": "7",
      "type": "1",
      "x": "-56.5",
      "z": "-9.609375",
      "y": "69.5",
      "roll": "0",
      "pitch": "0",
      "turn": "0",
      "id": "noname",
      "script": "pinetreeTeresa.s"
    },
    {
      "template": "7",
      "type": "1",
      "x": "-45.5",
      "z": "-9.609375",
      "y": "94.5",
      "roll": "0",
      "pitch": "0",
      "turn": "0",
      "id": "noname",
      "script": "pinetreeTeresa.s"
    },
    {
      "template": "7",
      "type": "1",
      "x": "-56.5",
      "z": "-9.609375",
      "y": "86.5",
      "roll": "0",
      "pitch": "0",
      "turn": "0",
      "id": "noname",
      "script": "pinetreeTeresa.s"
    },
    {
      "template": "7",
      "type": "1",
      "x": "-31.5",
      "z": "-9.609375",
      "y": "49.5",
      "roll": "0",
      "pitch": "0",
      "turn": "0",
      "id": "noname",
      "script": "pinetreeTeresa.s"
    },
    {
      "template": "7",
      "type": "1",
      "x": "-16.5",
      "z": "-9.609375",
      "y": "51.5",
      "roll": "0",
      "pitch": "0",
      "turn": "0",
      "id": "noname",
      "script": "pinetreeTeresa.s"
    },
    {
      "template": "7",
      "type": "1",
      "x": "-16.5",
      "z": "-9.609375",
      "y": "61.5",
      "roll": "0",
      "pitch": "0",
      "turn": "0",
      "id": "noname",
      "script": "pinetreeTeresa.s"
    },
    {
      "template": "7",
      "type": "1",
      "x": "-23.5",
      "z": "-9.609375",
      "y": "63.5",
      "roll": "0",
      "pitch": "0",
      "turn": "0",
      "id": "noname",
      "script": "pinetreeTeresa.s"
    },
    {
      "template": "7",
      "type": "1",
      "x": "-12.5",
      "z": "-9.609375",
      "y": "78.5",
      "roll": "0",
      "pitch": "0",
      "turn": "0",
      "id": "noname",
      "script": "pinetreeTeresa.s"
    },
    {
      "template": "7",
      "type": "1",
      "x": "-44.5",
      "z": "-10",
      "y": "64.5",
      "roll": "0",
      "pitch": "0",
      "turn": "0",
      "id": "noname",
      "script": "pinetreeTeresa.s"
    },
    {
      "template": "7",
      "type": "1",
      "x": "-44.5",
      "z": "-10",
      "y": "60.5",
      "roll": "0",
      "pitch": "0",
      "turn": "0",
      "id": "noname",
      "script": "pinetreeTeresa.s"
    },
    {
      "template": "7",
      "type": "1",
      "x": "-40.5",
      "z": "-10",
      "y": "63.5",
      "roll": "0",
      "pitch": "0",
      "turn": "0",
      "id": "noname",
      "script": "pinetreeTeresa.s"
    },
    {
      "template": "7",
      "type": "1",
      "x": "-42.5",
      "z": "-10",
      "y": "61.5",
      "roll": "0",
      "pitch": "0",
      "turn": "0",
      "id": "noname",
      "script": "pinetreeTeresa.s"
    },
    {
      "template": "7",
      "type": "1",
      "x": "-40.5",
      "z": "-10",
      "y": "60.5",
      "roll": "0",
      "pitch": "0",
      "turn": "0",
      "id": "noname",
      "script": "pinetreeTeresa.s"
    },
    {
      "template": "7",
      "type": "1",
      "x": "-40.5",
      "z": "-10",
      "y": "66.5",
      "roll": "0",
      "pitch": "0",
      "turn": "0",
      "id": "noname",
      "script": "pinetreeTeresa.s"
    },
    {
      "template": "7",
      "type": "1",
      "x": "-38.5",
      "z": "-10",
      "y": "76.5",
      "roll": "0",
      "pitch": "0",
      "turn": "0",
      "id": "noname",
      "script": "pinetreeTeresa.s"
    },
    {
      "template": "7",
      "type": "1",
      "x": "-38.5",
      "z": "-10",
      "y": "71.5",
      "roll": "0",
      "pitch": "0",
      "turn": "0",
      "id": "noname",
      "script": "pinetreeTeresa.s"
    },
    {
      "template": "7",
      "type": "1",
      "x": "-38.5",
      "z": "-10",
      "y": "68.5",
      "roll": "0",
      "pitch": "0",
      "turn": "0",
      "id": "noname",
      "script": "pinetreeTeresa.s"
    },
    {
      "template": "7",
      "type": "1",
      "x": "-38.5",
      "z": "-10",
      "y": "65.5",
      "roll": "0",
      "pitch": "0",
      "turn": "0",
      "id": "noname",
      "script": "pinetreeTeresa.s"
    },
    {
      "template": "7",
      "type": "1",
      "x": "-38.5",
      "z": "-10",
      "y": "61.5",
      "roll": "0",
      "pitch": "0",
      "turn": "0",
      "id": "noname",
      "script": "pinetreeTeresa.s"
    },
    {
      "template": "7",
      "type": "1",
      "x": "-36.5",
      "z": "-10",
      "y": "60.5",
      "roll": "0",
      "pitch": "0",
      "turn": "0",
      "id": "noname",
      "script": "pinetreeTeresa.s"
    },
    {
      "template": "7",
      "type": "1",
      "x": "-36.5",
      "z": "-10",
      "y": "63.5",
      "roll": "0",
      "pitch": "0",
      "turn": "0",
      "id": "noname",
      "script": "pinetreeTeresa.s"
    },
    {
      "template": "7",
      "type": "1",
      "x": "-36.5",
      "z": "-10",
      "y": "66.5",
      "roll": "0",
      "pitch": "0",
      "turn": "0",
      "id": "noname",
      "script": "pinetreeTeresa.s"
    },
    {
      "template": "7",
      "type": "1",
      "x": "-36.5",
      "z": "-10",
      "y": "69.5",
      "roll": "0",
      "pitch": "0",
      "turn": "0",
      "id": "noname",
      "script": "pinetreeTeresa.s"
    },
    {
      "template": "7",
      "type": "1",
      "x": "-36.5",
      "z": "-10",
      "y": "72.5",
      "roll": "0",
      "pitch": "0",
      "turn": "0",
      "id": "noname",
      "script": "pinetreeTeresa.s"
    },
    {
      "template": "7",
      "type": "1",
      "x": "-36.5",
      "z": "-10",
      "y": "75.5",
      "roll": "0",
      "pitch": "0",
      "turn": "0",
      "id": "noname",
      "script": "pinetreeTeresa.s"
    },
    {
      "template": "7",
      "type": "1",
      "x": "-36.5",
      "z": "-10",
      "y": "78.5",
      "roll": "0",
      "pitch": "0",
      "turn": "0",
      "id": "noname",
      "script": "pinetreeTeresa.s"
    },
    {
      "template": "1019",
      "type": "1",
      "x": "-105.5",
      "z": "-8.125",
      "y": "43.5",
      "roll": "0",
      "pitch": "0",
      "turn": "0",
      "id": "noname",
      "script": "DFtreeeTeresa.s"
    },
    {
      "template": "1019",
      "type": "1",
      "x": "-105.5",
      "z": "-8.125",
      "y": "41.5",
      "roll": "0",
      "pitch": "0",
      "turn": "0",
      "id": "noname",
      "script": "DFtreeeTeresa.s"
    },
    {
      "template": "1019",
      "type": "1",
      "x": "-105.5",
      "z": "-8.359375",
      "y": "39.5",
      "roll": "0",
      "pitch": "0",
      "turn": "5",
      "id": "noname",
      "script": "DFtreeeTeresa.s"
    },
    {
      "template": "1019",
      "type": "1",
      "x": "-104.5",
      "z": "-8.359375",
      "y": "37.5",
      "roll": "0",
      "pitch": "0",
      "turn": "25",
      "id": "noname",
      "script": "DFtreeeTeresa.s"
    },
    {
      "template": "1019",
      "type": "1",
      "x": "-103.5",
      "z": "-8.359375",
      "y": "35.5",
      "roll": "0",
      "pitch": "0",
      "turn": "25",
      "id": "noname",
      "script": "DFtreeeTeresa.s"
    },
    {
      "template": "1019",
      "type": "1",
      "x": "-102.5",
      "z": "-8.359375",
      "y": "33.5",
      "roll": "0",
      "pitch": "0",
      "turn": "25",
      "id": "noname",
      "script": "DFtreeeTeresa.s"
    },
    {
      "template": "1019",
      "type": "1",
      "x": "-100.5",
      "z": "-8.359375",
      "y": "31.5",
      "roll": "0",
      "pitch": "0",
      "turn": "25",
      "id": "noname",
      "script": "DFtreeeTeresa.s"
    },
    {
      "template": "1019",
      "type": "1",
      "x": "-34.5",
      "z": "-8.828125",
      "y": "104.5",
      "roll": "0",
      "pitch": "0",
      "turn": "-65",
      "id": "noname",
      "script": "DFtreeeTeresa.s"
    },
    {
      "template": "1018",
      "type": "1",
      "x": "-32.5",
      "z": "-8.828125",
      "y": "104.5",
      "roll": "0",
      "pitch": "0",
      "turn": "-65",
      "id": "noname",
      "script": "DFtree2Teresa.s"
    },
    {
      "template": "1019",
      "type": "1",
      "x": "-30.5",
      "z": "-8.828125",
      "y": "104.5",
      "roll": "0",
      "pitch": "0",
      "turn": "-65",
      "id": "noname",
      "script": "DFtreeTeresa.s"
    },
    {
      "template": "1018",
      "type": "1",
      "x": "-28.5",
      "z": "-8.828125",
      "y": "104.5",
      "roll": "0",
      "pitch": "0",
      "turn": "-65",
      "id": "noname",
      "script": "DFtree2Teresa.s"
    },
    {
      "template": "1019",
      "type": "1",
      "x": "-26.5",
      "z": "-8.828125",
      "y": "104.5",
      "roll": "0",
      "pitch": "0",
      "turn": "-65",
      "id": "noname",
      "script": "DFtreeTeresa.s"
    },
    {
      "template": "1019",
      "type": "1",
      "x": "-12.5",
      "z": "-8.3984375",
      "y": "104.5",
      "roll": "0",
      "pitch": "0",
      "turn": "-65",
      "id": "noname",
      "script": "DFtreeTeresa.s"
    },
    {
      "template": "1018",
      "type": "1",
      "x": "-14.5",
      "z": "-8.3984375",
      "y": "104.5",
      "roll": "0",
      "pitch": "0",
      "turn": "-65",
      "id": "noname",
      "script": "DFtree2Teresa.s"
    },
    {
      "template": "1018",
      "type": "1",
      "x": "-16.5",
      "z": "-8.3984375",
      "y": "104.5",
      "roll": "0",
      "pitch": "0",
      "turn": "-65",
      "id": "noname",
      "script": "DFtree2Teresa.s"
    },
    {
      "template": "1016",
      "type": "11",
      "x": "-118.6953125",
      "z": "-6.4453125",
      "y": "61.1328125",
      "roll": "0",
      "pitch": "0",
      "turn": "126",
      "id": "LGate",
      "script": "drgnfld\\drgn_gate01.s"
    },
    {
      "template": "1016",
      "type": "11",
      "x": "-118.4609375",
      "z": "-6.40625",
      "y": "66.8671875",
      "roll": "0",
      "pitch": "0",
      "turn": "0",
      "id": "RGate",
      "script": "drgnfld\\drgn_gate02.s"
    },
    {
      "template": "1017",
      "type": "1",
      "x": "-16.71875",
      "z": "-7.421875",
      "y": "114.1484375",
      "roll": "0",
      "pitch": "0",
      "turn": "0",
      "id": "noname",
      "script": "kingmemorialgate02.s"
    },
    {
      "template": "1019",
      "type": "1",
      "x": "-24.5",
      "z": "-8.3984375",
      "y": "104.5",
      "roll": "0",
      "pitch": "0",
      "turn": "-65",
      "id": "noname",
      "script": "DFtreeorialgate02.s"
    },
    {
      "template": "1019",
      "type": "1",
      "x": "-22.5",
      "z": "-8.3984375",
      "y": "104.5",
      "roll": "0",
      "pitch": "0",
      "turn": "-65",
      "id": "noname",
      "script": "DFtreeorialgate02.s"
    },
    {
      "template": "1019",
      "type": "1",
      "x": "-20.5",
      "z": "-8.3984375",
      "y": "104.5",
      "roll": "0",
      "pitch": "0",
      "turn": "-65",
      "id": "noname",
      "script": "DFtreeorialgate02.s"
    },
    {
      "template": "1019",
      "type": "1",
      "x": "-18.5",
      "z": "-8.3984375",
      "y": "104.5",
      "roll": "0",
      "pitch": "0",
      "turn": "-65",
      "id": "noname",
      "script": "DFtreeorialgate02.s"
    },
    {
      "template": "1019",
      "type": "1",
      "x": "-15.5",
      "z": "-8.828125",
      "y": "94.5",
      "roll": "0",
      "pitch": "0",
      "turn": "-65",
      "id": "noname",
      "script": "DFtreeorialgate02.s"
    },
    {
      "template": "1018",
      "type": "1",
      "x": "-17.5",
      "z": "-8.828125",
      "y": "94.5",
      "roll": "0",
      "pitch": "0",
      "turn": "-65",
      "id": "noname",
      "script": "DFtree2rialgate02.s"
    },
    {
      "template": "1019",
      "type": "1",
      "x": "-19.5",
      "z": "-8.828125",
      "y": "94.5",
      "roll": "0",
      "pitch": "0",
      "turn": "-65",
      "id": "noname",
      "script": "DFtreerialgate02.s"
    },
    {
      "template": "1018",
      "type": "1",
      "x": "-21.5",
      "z": "-8.828125",
      "y": "94.5",
      "roll": "0",
      "pitch": "0",
      "turn": "-65",
      "id": "noname",
      "script": "DFtree2rialgate02.s"
    },
    {
      "template": "1019",
      "type": "1",
      "x": "-23.5",
      "z": "-8.828125",
      "y": "94.5",
      "roll": "0",
      "pitch": "0",
      "turn": "-65",
      "id": "noname",
      "script": "DFtreerialgate02.s"
    },
    {
      "template": "1018",
      "type": "1",
      "x": "-25.5",
      "z": "-8.828125",
      "y": "94.5",
      "roll": "0",
      "pitch": "0",
      "turn": "-65",
      "id": "noname",
      "script": "DFtree2rialgate02.s"
    },
    {
      "template": "1019",
      "type": "1",
      "x": "-27.5",
      "z": "-8.828125",
      "y": "94.5",
      "roll": "0",
      "pitch": "0",
      "turn": "-65",
      "id": "noname",
      "script": "DFtreerialgate02.s"
    },
    {
      "template": "1018",
      "type": "1",
      "x": "-24.5",
      "z": "-8.828125",
      "y": "85.5",
      "roll": "0",
      "pitch": "0",
      "turn": "0",
      "id": "noname",
      "script": "DFtree2rialgate02.s"
    },
    {
      "template": "1018",
      "type": "1",
      "x": "-24.5",
      "z": "-8.828125",
      "y": "83.5",
      "roll": "0",
      "pitch": "0",
      "turn": "0",
      "id": "noname",
      "script": "DFtree2rialgate02.s"
    },
    {
      "template": "1018",
      "type": "1",
      "x": "-24.5",
      "z": "-8.828125",
      "y": "81.5",
      "roll": "0",
      "pitch": "0",
      "turn": "0",
      "id": "noname",
      "script": "DFtree2rialgate02.s"
    },
    {
      "template": "1018",
      "type": "1",
      "x": "-24.5",
      "z": "-8.828125",
      "y": "79.5",
      "roll": "0",
      "pitch": "0",
      "turn": "0",
      "id": "noname",
      "script": "DFtree2rialgate02.s"
    },
    {
      "template": "1018",
      "type": "1",
      "x": "-24.5",
      "z": "-8.828125",
      "y": "77.5",
      "roll": "0",
      "pitch": "0",
      "turn": "0",
      "id": "noname",
      "script": "DFtree2rialgate02.s"
    },
    {
      "template": "1019",
      "type": "1",
      "x": "-34.5",
      "z": "-8.671875",
      "y": "87.5",
      "roll": "0",
      "pitch": "0",
      "turn": "0",
      "id": "noname",
      "script": "DFtreerialgate02.s"
    },
    {
      "template": "1019",
      "type": "1",
      "x": "-34.5",
      "z": "-8.671875",
      "y": "85.5",
      "roll": "0",
      "pitch": "0",
      "turn": "0",
      "id": "noname",
      "script": "DFtreerialgate02.s"
    },
    {
      "template": "1019",
      "type": "1",
      "x": "-34.5",
      "z": "-8.671875",
      "y": "83.5",
      "roll": "0",
      "pitch": "0",
      "turn": "0",
      "id": "noname",
      "script": "DFtreerialgate02.s"
    },
    {
      "template": "1018",
      "type": "1",
      "x": "-34.5",
      "z": "-8.671875",
      "y": "81.5",
      "roll": "0",
      "pitch": "0",
      "turn": "0",
      "id": "noname",
      "script": "DFtree2rialgate02.s"
    },
    {
      "template": "1018",
      "type": "1",
      "x": "-34.5",
      "z": "-8.671875",
      "y": "79.5",
      "roll": "0",
      "pitch": "0",
      "turn": "0",
      "id": "noname",
      "script": "DFtree2rialgate02.s"
    },
    {
      "template": "1018",
      "type": "1",
      "x": "-34.5",
      "z": "-8.671875",
      "y": "77.5",
      "roll": "0",
      "pitch": "0",
      "turn": "0",
      "id": "noname",
      "script": "DFtree2rialgate02.s"
    },
    {
      "template": "1018",
      "type": "1",
      "x": "-34.5",
      "z": "-8.671875",
      "y": "75.5",
      "roll": "0",
      "pitch": "0",
      "turn": "0",
      "id": "noname",
      "script": "DFtree2rialgate02.s"
    },
    {
      "template": "1018",
      "type": "1",
      "x": "-34.5",
      "z": "-8.671875",
      "y": "73.5",
      "roll": "0",
      "pitch": "0",
      "turn": "0",
      "id": "noname",
      "script": "DFtree2rialgate02.s"
    },
    {
      "template": "1018",
      "type": "1",
      "x": "-34.5",
      "z": "-8.671875",
      "y": "71.5",
      "roll": "0",
      "pitch": "0",
      "turn": "0",
      "id": "noname",
      "script": "DFtree2rialgate02.s"
    },
    {
      "template": "1018",
      "type": "1",
      "x": "-34.5",
      "z": "-8.671875",
      "y": "69.5",
      "roll": "0",
      "pitch": "0",
      "turn": "0",
      "id": "noname",
      "script": "DFtree2rialgate02.s"
    },
    {
      "template": "1019",
      "type": "1",
      "x": "-34.5",
      "z": "-8.671875",
      "y": "67.5",
      "roll": "0",
      "pitch": "0",
      "turn": "0",
      "id": "noname",
      "script": "DFtreerialgate02.s"
    },
    {
      "template": "1019",
      "type": "1",
      "x": "-34.5",
      "z": "-8.671875",
      "y": "65.5",
      "roll": "0",
      "pitch": "0",
      "turn": "0",
      "id": "noname",
      "script": "DFtreerialgate02.s"
    },
    {
      "template": "1019",
      "type": "1",
      "x": "-34.5",
      "z": "-8.671875",
      "y": "63.5",
      "roll": "0",
      "pitch": "0",
      "turn": "0",
      "id": "noname",
      "script": "DFtreerialgate02.s"
    },
    {
      "template": "1019",
      "type": "1",
      "x": "-34.5",
      "z": "-8.671875",
      "y": "61.5",
      "roll": "0",
      "pitch": "0",
      "turn": "0",
      "id": "noname",
      "script": "DFtreerialgate02.s"
    },
    {
      "template": "1018",
      "type": "1",
      "x": "-34.5",
      "z": "-8.671875",
      "y": "59.5",
      "roll": "0",
      "pitch": "0",
      "turn": "0",
      "id": "noname",
      "script": "DFtree2rialgate02.s"
    },
    {
      "template": "1018",
      "type": "1",
      "x": "-34.5",
      "z": "-8.671875",
      "y": "57.5",
      "roll": "0",
      "pitch": "0",
      "turn": "0",
      "id": "noname",
      "script": "DFtree2rialgate02.s"
    },
    {
      "template": "1019",
      "type": "1",
      "x": "-36.5",
      "z": "-8.6328125",
      "y": "57.5",
      "roll": "0",
      "pitch": "0",
      "turn": "-65",
      "id": "noname",
      "script": "DFtreerialgate02.s"
    },
    {
      "template": "1019",
      "type": "1",
      "x": "-38.5",
      "z": "-8.6328125",
      "y": "57.5",
      "roll": "0",
      "pitch": "0",
      "turn": "-65",
      "id": "noname",
      "script": "DFtreerialgate02.s"
    },
    {
      "template": "1018",
      "type": "1",
      "x": "-40.5",
      "z": "-8.6328125",
      "y": "57.5",
      "roll": "0",
      "pitch": "0",
      "turn": "-65",
      "id": "noname",
      "script": "DFtree2rialgate02.s"
    },
    {
      "template": "1018",
      "type": "1",
      "x": "-42.5",
      "z": "-8.6328125",
      "y": "57.5",
      "roll": "0",
      "pitch": "0",
      "turn": "-65",
      "id": "noname",
      "script": "DFtree2rialgate02.s"
    },
    {
      "template": "1019",
      "type": "1",
      "x": "-44.5",
      "z": "-8.6328125",
      "y": "57.5",
      "roll": "0",
      "pitch": "0",
      "turn": "-65",
      "id": "noname",
      "script": "DFtreerialgate02.s"
    },
    {
      "template": "1018",
      "type": "1",
      "x": "-46.5",
      "z": "-8.6328125",
      "y": "57.5",
      "roll": "0",
      "pitch": "0",
      "turn": "-65",
      "id": "noname",
      "script": "DFtree2rialgate02.s"
    },
    {
      "template": "1019",
      "type": "1",
      "x": "-48.5",
      "z": "-8.6328125",
      "y": "57.5",
      "roll": "0",
      "pitch": "0",
      "turn": "-65",
      "id": "noname",
      "script": "DFtreerialgate02.s"
    },
    {
      "template": "1019",
      "type": "1",
      "x": "-50.5",
      "z": "-8.6328125",
      "y": "57.5",
      "roll": "0",
      "pitch": "0",
      "turn": "-65",
      "id": "noname",
      "script": "DFtreerialgate02.s"
    },
    {
      "template": "1019",
      "type": "1",
      "x": "-52.5",
      "z": "-8.6328125",
      "y": "57.5",
      "roll": "0",
      "pitch": "0",
      "turn": "-65",
      "id": "noname",
      "script": "DFtreerialgate02.s"
    },
    {
      "template": "1019",
      "type": "1",
      "x": "-54.5",
      "z": "-8.6328125",
      "y": "57.5",
      "roll": "0",
      "pitch": "0",
      "turn": "-65",
      "id": "noname",
      "script": "DFtreerialgate02.s"
    },
    {
      "template": "1019",
      "type": "1",
      "x": "-56.5",
      "z": "-8.6328125",
      "y": "57.5",
      "roll": "0",
      "pitch": "0",
      "turn": "-65",
      "id": "noname",
      "script": "DFtreerialgate02.s"
    },
    {
      "template": "1018",
      "type": "1",
      "x": "-58.5",
      "z": "-8.7109375",
      "y": "57.5",
      "roll": "0",
      "pitch": "0",
      "turn": "0",
      "id": "noname",
      "script": "DFtree2rialgate02.s"
    },
    {
      "template": "1018",
      "type": "1",
      "x": "-58.5",
      "z": "-8.7109375",
      "y": "55.5",
      "roll": "0",
      "pitch": "0",
      "turn": "0",
      "id": "noname",
      "script": "DFtree2rialgate02.s"
    },
    {
      "template": "1019",
      "type": "1",
      "x": "-58.5",
      "z": "-8.7109375",
      "y": "53.5",
      "roll": "0",
      "pitch": "0",
      "turn": "0",
      "id": "noname",
      "script": "DFtreerialgate02.s"
    },
    {
      "template": "1019",
      "type": "1",
      "x": "-58.5",
      "z": "-8.7109375",
      "y": "51.5",
      "roll": "0",
      "pitch": "0",
      "turn": "0",
      "id": "noname",
      "script": "DFtreerialgate02.s"
    },
    {
      "template": "1019",
      "type": "1",
      "x": "-58.5",
      "z": "-8.7109375",
      "y": "49.5",
      "roll": "0",
      "pitch": "0",
      "turn": "0",
      "id": "noname",
      "script": "DFtreerialgate02.s"
    },
    {
      "template": "1018",
      "type": "1",
      "x": "-58.5",
      "z": "-8.7109375",
      "y": "47.5",
      "roll": "0",
      "pitch": "0",
      "turn": "0",
      "id": "noname",
      "script": "DFtree2rialgate02.s"
    },
    {
      "template": "1018",
      "type": "1",
      "x": "-58.5",
      "z": "-8.7109375",
      "y": "45.5",
      "roll": "0",
      "pitch": "0",
      "turn": "0",
      "id": "noname",
      "script": "DFtree2rialgate02.s"
    },
    {
      "template": "1018",
      "type": "1",
      "x": "-58.5",
      "z": "-8.7109375",
      "y": "43.5",
      "roll": "0",
      "pitch": "0",
      "turn": "0",
      "id": "noname",
      "script": "DFtree2rialgate02.s"
    },
    {
      "template": "1018",
      "type": "1",
      "x": "-58.5",
      "z": "-8.7109375",
      "y": "41.5",
      "roll": "0",
      "pitch": "0",
      "turn": "0",
      "id": "noname",
      "script": "DFtree2rialgate02.s"
    },
    {
      "template": "1019",
      "type": "1",
      "x": "-6.5",
      "z": "-8.7109375",
      "y": "46.5",
      "roll": "0",
      "pitch": "0",
      "turn": "-30",
      "id": "noname",
      "script": "DFtreerialgate02.s"
    },
    {
      "template": "1019",
      "type": "1",
      "x": "-8.5",
      "z": "-8.7109375",
      "y": "44.5",
      "roll": "0",
      "pitch": "0",
      "turn": "-30",
      "id": "noname",
      "script": "DFtreerialgate02.s"
    },
    {
      "template": "1019",
      "type": "1",
      "x": "-10.5",
      "z": "-8.7109375",
      "y": "42.5",
      "roll": "0",
      "pitch": "0",
      "turn": "-30",
      "id": "noname",
      "script": "DFtreerialgate02.s"
    },
    {
      "template": "1019",
      "type": "1",
      "x": "-12.5",
      "z": "-8.7109375",
      "y": "40.5",
      "roll": "0",
      "pitch": "0",
      "turn": "-30",
      "id": "noname",
      "script": "DFtreerialgate02.s"
    },
    {
      "template": "1019",
      "type": "1",
      "x": "-14.5",
      "z": "-8.7109375",
      "y": "38.5",
      "roll": "0",
      "pitch": "0",
      "turn": "-30",
      "id": "noname",
      "script": "DFtreerialgate02.s"
    },
    {
      "template": "1019",
      "type": "1",
      "x": "-16.5",
      "z": "-8.7109375",
      "y": "37.5",
      "roll": "0",
      "pitch": "0",
      "turn": "-30",
      "id": "noname",
      "script": "DFtreerialgate02.s"
    },
    {
      "template": "1019",
      "type": "1",
      "x": "-18.5",
      "z": "-8.7109375",
      "y": "35.5",
      "roll": "0",
      "pitch": "0",
      "turn": "-30",
      "id": "noname",
      "script": "DFtreerialgate02.s"
    },
    {
      "template": "1019",
      "type": "1",
      "x": "-20.5",
      "z": "-8.7109375",
      "y": "33.5",
      "roll": "0",
      "pitch": "0",
      "turn": "-30",
      "id": "noname",
      "script": "DFtreerialgate02.s"
    },
    {
      "template": "1019",
      "type": "1",
      "x": "-21.875",
      "z": "-9.8828125",
      "y": "32.5",
      "roll": "0",
      "pitch": "0",
      "turn": "-30",
      "id": "noname",
      "script": "DFtreerialgate02.s"
    },
    {
      "template": "1018",
      "type": "1",
      "x": "-49.5",
      "z": "-9.8828125",
      "y": "49.5",
      "roll": "0",
      "pitch": "0",
      "turn": "30",
      "id": "noname",
      "script": "DFtree2rialgate02.s"
    },
    {
      "template": "1018",
      "type": "1",
      "x": "-47.5",
      "z": "-9.8828125",
      "y": "47.5",
      "roll": "0",
      "pitch": "0",
      "turn": "30",
      "id": "noname",
      "script": "DFtree2rialgate02.s"
    },
    {
      "template": "1018",
      "type": "1",
      "x": "-45.5",
      "z": "-9.8828125",
      "y": "45.5",
      "roll": "0",
      "pitch": "0",
      "turn": "30",
      "id": "noname",
      "script": "DFtree2rialgate02.s"
    },
    {
      "template": "1018",
      "type": "1",
      "x": "-44.5",
      "z": "-9.8828125",
      "y": "43.5",
      "roll": "0",
      "pitch": "0",
      "turn": "30",
      "id": "noname",
      "script": "DFtree2rialgate02.s"
    },
    {
      "template": "1018",
      "type": "1",
      "x": "-42.5",
      "z": "-9.8828125",
      "y": "41.5",
      "roll": "0",
      "pitch": "0",
      "turn": "30",
      "id": "noname",
      "script": "DFtree2rialgate02.s"
    },
    {
      "template": "1018",
      "type": "1",
      "x": "-40.5",
      "z": "-9.8828125",
      "y": "39.5",
      "roll": "0",
      "pitch": "0",
      "turn": "30",
      "id": "noname",
      "script": "DFtree2rialgate02.s"
    },
    {
      "template": "1018",
      "type": "1",
      "x": "-38.5",
      "z": "-9.8828125",
      "y": "37.5",
      "roll": "0",
      "pitch": "0",
      "turn": "30",
      "id": "noname",
      "script": "DFtree2rialgate02.s"
    },
    {
      "template": "1018",
      "type": "1",
      "x": "-37.5",
      "z": "-8.7109375",
      "y": "35.5",
      "roll": "0",
      "pitch": "0",
      "turn": "30",
      "id": "noname",
      "script": "DFtree2rialgate02.s"
    },
    {
      "template": "1018",
      "type": "1",
      "x": "-35.5",
      "z": "-8.7109375",
      "y": "33.5",
      "roll": "0",
      "pitch": "0",
      "turn": "30",
      "id": "noname",
      "script": "DFtree2rialgate02.s"
    },
    {
      "template": "1018",
      "type": "1",
      "x": "-33.5",
      "z": "-8.7109375",
      "y": "31.5",
      "roll": "0",
      "pitch": "0",
      "turn": "30",
      "id": "noname",
      "script": "DFtree2rialgate02.s"
    },
    {
      "template": "1018",
      "type": "1",
      "x": "-31.5",
      "z": "-8.7109375",
      "y": "29.5",
      "roll": "0",
      "pitch": "0",
      "turn": "30",
      "id": "noname",
      "script": "DFtree2rialgate02.s"
    },
    {
      "template": "1018",
      "type": "1",
      "x": "-30.28125",
      "z": "-9.140625",
      "y": "27.890625",
      "roll": "0",
      "pitch": "0",
      "turn": "25",
      "id": "noname",
      "script": "DFtree2rialgate02.s"
    },
    {
      "template": "1019",
      "type": "1",
      "x": "-31.5",
      "z": "-9.1015625",
      "y": "26.5",
      "roll": "0",
      "pitch": "0",
      "turn": "-30",
      "id": "noname",
      "script": "DFtreerialgate02.s"
    },
    {
      "template": "1019",
      "type": "1",
      "x": "-33.5",
      "z": "-9.1015625",
      "y": "24.5",
      "roll": "0",
      "pitch": "0",
      "turn": "-30",
      "id": "noname",
      "script": "DFtreerialgate02.s"
    },
    {
      "template": "1019",
      "type": "1",
      "x": "-35.5",
      "z": "-9.1015625",
      "y": "22.5",
      "roll": "0",
      "pitch": "0",
      "turn": "-30",
      "id": "noname",
      "script": "DFtreerialgate02.s"
    },
    {
      "template": "1019",
      "type": "1",
      "x": "-37.5",
      "z": "-9.1015625",
      "y": "20.5",
      "roll": "0",
      "pitch": "0",
      "turn": "-30",
      "id": "noname",
      "script": "DFtreerialgate02.s"
    },
    {
      "template": "1019",
      "type": "1",
      "x": "-39.5",
      "z": "-9.1015625",
      "y": "18.5",
      "roll": "0",
      "pitch": "0",
      "turn": "-30",
      "id": "noname",
      "script": "DFtreerialgate02.s"
    },
    {
      "template": "1019",
      "type": "1",
      "x": "-41.5",
      "z": "-9.1015625",
      "y": "16.5",
      "roll": "0",
      "pitch": "0",
      "turn": "-30",
      "id": "noname",
      "script": "DFtreerialgate02.s"
    },
    {
      "template": "1018",
      "type": "1",
      "x": "-73.5",
      "z": "-8.7109375",
      "y": "27.5",
      "roll": "0",
      "pitch": "0",
      "turn": "-65",
      "id": "noname",
      "script": "DFtree2rialgate02.s"
    },
    {
      "template": "1018",
      "type": "1",
      "x": "-75.5",
      "z": "-8.7109375",
      "y": "27.5",
      "roll": "0",
      "pitch": "0",
      "turn": "-65",
      "id": "noname",
      "script": "DFtree2rialgate02.s"
    },
    {
      "template": "1018",
      "type": "1",
      "x": "-77.5",
      "z": "-8.7109375",
      "y": "27.5",
      "roll": "0",
      "pitch": "0",
      "turn": "-65",
      "id": "noname",
      "script": "DFtree2rialgate02.s"
    },
    {
      "template": "1018",
      "type": "1",
      "x": "-79.5",
      "z": "-8.7109375",
      "y": "27.5",
      "roll": "0",
      "pitch": "0",
      "turn": "-65",
      "id": "noname",
      "script": "DFtree2rialgate02.s"
    },
    {
      "template": "1018",
      "type": "1",
      "x": "-81.5",
      "z": "-8.7109375",
      "y": "27.5",
      "roll": "0",
      "pitch": "0",
      "turn": "-65",
      "id": "noname",
      "script": "DFtree2rialgate02.s"
    },
    {
      "template": "1019",
      "type": "1",
      "x": "-83.5",
      "z": "-8.7109375",
      "y": "27.5",
      "roll": "0",
      "pitch": "0",
      "turn": "-65",
      "id": "noname",
      "script": "DFtreerialgate02.s"
    },
    {
      "template": "1019",
      "type": "1",
      "x": "-85.5",
      "z": "-8.7109375",
      "y": "27.5",
      "roll": "0",
      "pitch": "0",
      "turn": "-65",
      "id": "noname",
      "script": "DFtreerialgate02.s"
    },
    {
      "template": "1019",
      "type": "1",
      "x": "-87.5",
      "z": "-8.7109375",
      "y": "27.5",
      "roll": "0",
      "pitch": "0",
      "turn": "-65",
      "id": "noname",
      "script": "DFtreerialgate02.s"
    },
    {
      "template": "1018",
      "type": "1",
      "x": "-89.5",
      "z": "-8.7109375",
      "y": "27.5",
      "roll": "0",
      "pitch": "0",
      "turn": "-65",
      "id": "noname",
      "script": "DFtree2rialgate02.s"
    },
    {
      "template": "1018",
      "type": "1",
      "x": "-91.5",
      "z": "-8.7109375",
      "y": "27.5",
      "roll": "0",
      "pitch": "0",
      "turn": "-65",
      "id": "noname",
      "script": "DFtree2rialgate02.s"
    },
    {
      "template": "1018",
      "type": "1",
      "x": "-93.5",
      "z": "-8.7109375",
      "y": "27.5",
      "roll": "0",
      "pitch": "0",
      "turn": "-65",
      "id": "noname",
      "script": "DFtree2rialgate02.s"
    },
    {
      "template": "1019",
      "type": "1",
      "x": "-95.5",
      "z": "-8.7109375",
      "y": "27.5",
      "roll": "0",
      "pitch": "0",
      "turn": "-65",
      "id": "noname",
      "script": "DFtreerialgate02.s"
    },
    {
      "template": "1019",
      "type": "1",
      "x": "-97.5",
      "z": "-8.7109375",
      "y": "27.5",
      "roll": "0",
      "pitch": "0",
      "turn": "-65",
      "id": "noname",
      "script": "DFtreerialgate02.s"
    },
    {
      "template": "1019",
      "type": "1",
      "x": "-71.5",
      "z": "-8.7109375",
      "y": "27.5",
      "roll": "0",
      "pitch": "0",
      "turn": "-65",
      "id": "noname",
      "script": "DFtreerialgate02.s"
    },
    {
      "template": "1019",
      "type": "1",
      "x": "-69.5",
      "z": "-8.7109375",
      "y": "27.5",
      "roll": "0",
      "pitch": "0",
      "turn": "-65",
      "id": "noname",
      "script": "DFtreerialgate02.s"
    },
    {
      "template": "1018",
      "type": "1",
      "x": "-68.5",
      "z": "-9.0625",
      "y": "29.5",
      "roll": "0",
      "pitch": "0",
      "turn": "-15.5",
      "id": "noname",
      "script": "DFtree2rialgate02.s"
    },
    {
      "template": "1018",
      "type": "1",
      "x": "-67.5",
      "z": "-9.0625",
      "y": "31.5",
      "roll": "0",
      "pitch": "0",
      "turn": "-15.5",
      "id": "noname",
      "script": "DFtree2rialgate02.s"
    },
    {
      "template": "1018",
      "type": "1",
      "x": "-66.5",
      "z": "-9.0625",
      "y": "33.5",
      "roll": "0",
      "pitch": "0",
      "turn": "-15.5",
      "id": "noname",
      "script": "DFtree2rialgate02.s"
    },
    {
      "template": "1018",
      "type": "1",
      "x": "-65.5",
      "z": "-9.0625",
      "y": "35.5",
      "roll": "0",
      "pitch": "0",
      "turn": "-15.5",
      "id": "noname",
      "script": "DFtree2rialgate02.s"
    },
    {
      "template": "1018",
      "type": "1",
      "x": "-68.5",
      "z": "-8.7109375",
      "y": "25.5",
      "roll": "0",
      "pitch": "0",
      "turn": "30",
      "id": "noname",
      "script": "DFtree2rialgate02.s"
    },
    {
      "template": "1018",
      "type": "1",
      "x": "-66.5",
      "z": "-9.8828125",
      "y": "23.5",
      "roll": "0",
      "pitch": "0",
      "turn": "30",
      "id": "noname",
      "script": "DFtree2rialgate02.s"
    },
    {
      "template": "1018",
      "type": "1",
      "x": "-64.5",
      "z": "-9.1015625",
      "y": "21.5",
      "roll": "0",
      "pitch": "0",
      "turn": "30",
      "id": "noname",
      "script": "DFtree2rialgate02.s"
    },
    {
      "template": "1018",
      "type": "1",
      "x": "-62.5",
      "z": "-10.2734375",
      "y": "19.5",
      "roll": "0",
      "pitch": "0",
      "turn": "30",
      "id": "noname",
      "script": "DFtree2rialgate02.s"
    },
    {
      "template": "1019",
      "type": "1",
      "x": "-98.5",
      "z": "-8.359375",
      "y": "29.5",
      "roll": "0",
      "pitch": "0",
      "turn": "25",
      "id": "noname",
      "script": "DFtreerialgate02.s"
    },
    {
      "template": "1018",
      "type": "1",
      "x": "-103.5",
      "z": "-8.3203125",
      "y": "44.71875",
      "roll": "0",
      "pitch": "0",
      "turn": "-45",
      "id": "noname",
      "script": "DFtree2rialgate02.s"
    },
    {
      "template": "1018",
      "type": "1",
      "x": "-101.5",
      "z": "-8.3203125",
      "y": "45.71875",
      "roll": "0",
      "pitch": "0",
      "turn": "-45",
      "id": "noname",
      "script": "DFtree2rialgate02.s"
    },
    {
      "template": "1018",
      "type": "1",
      "x": "-99.5",
      "z": "-8.3203125",
      "y": "46.71875",
      "roll": "0",
      "pitch": "0",
      "turn": "-45",
      "id": "noname",
      "script": "DFtree2rialgate02.s"
    },
    {
      "template": "1018",
      "type": "1",
      "x": "-97.5",
      "z": "-8.8671875",
      "y": "48.71875",
      "roll": "0",
      "pitch": "0",
      "turn": "-45",
      "id": "noname",
      "script": "DFtree2rialgate02.s"
    },
    {
      "template": "1018",
      "type": "1",
      "x": "-95.5",
      "z": "-8.8671875",
      "y": "49.71875",
      "roll": "0",
      "pitch": "0",
      "turn": "-45",
      "id": "noname",
      "script": "DFtree2rialgate02.s"
    },
    {
      "template": "1018",
      "type": "1",
      "x": "-93.5",
      "z": "-8.8671875",
      "y": "50.71875",
      "roll": "0",
      "pitch": "0",
      "turn": "-45",
      "id": "noname",
      "script": "DFtree2rialgate02.s"
    },
    {
      "template": "1019",
      "type": "1",
      "x": "-98.5",
      "z": "-8.7109375",
      "y": "25.5",
      "roll": "0",
      "pitch": "0",
      "turn": "-30",
      "id": "noname",
      "script": "DFtreerialgate02.s"
    },
    {
      "template": "1019",
      "type": "1",
      "x": "-100.5",
      "z": "-8.7109375",
      "y": "23.5",
      "roll": "0",
      "pitch": "0",
      "turn": "-30",
      "id": "noname",
      "script": "DFtreerialgate02.s"
    },
    {
      "template": "1019",
      "type": "1",
      "x": "-101.5",
      "z": "-8.7109375",
      "y": "21.5",
      "roll": "0",
      "pitch": "0",
      "turn": "-30",
      "id": "noname",
      "script": "DFtreerialgate02.s"
    },
    {
      "template": "1019",
      "type": "1",
      "x": "-103.5",
      "z": "-8.7109375",
      "y": "19.5",
      "roll": "0",
      "pitch": "0",
      "turn": "-30",
      "id": "noname",
      "script": "DFtreerialgate02.s"
    },
    {
      "template": "1019",
      "type": "1",
      "x": "-105.5",
      "z": "-8.7109375",
      "y": "17.5",
      "roll": "0",
      "pitch": "0",
      "turn": "-30",
      "id": "noname",
      "script": "DFtreerialgate02.s"
    },
    {
      "template": "1019",
      "type": "1",
      "x": "-106.5",
      "z": "-8.7109375",
      "y": "15.5",
      "roll": "0",
      "pitch": "0",
      "turn": "-30",
      "id": "noname",
      "script": "DFtreerialgate02.s"
    },
    {
      "template": "1019",
      "type": "1",
      "x": "-107.5",
      "z": "-9.8828125",
      "y": "13.5",
      "roll": "0",
      "pitch": "0",
      "turn": "-30",
      "id": "noname",
      "script": "DFtreerialgate02.s"
    },
    {
      "template": "1018",
      "type": "1",
      "x": "-110.5",
      "z": "-8.7109375",
      "y": "111.5",
      "roll": "0",
      "pitch": "0",
      "turn": "0",
      "id": "noname",
      "script": "DFtree2rialgate02.s"
    },
    {
      "template": "1018",
      "type": "1",
      "x": "-110.5",
      "z": "-8.7109375",
      "y": "108.5",
      "roll": "0",
      "pitch": "0",
      "turn": "0",
      "id": "noname",
      "script": "DFtree2rialgate02.s"
    },
    {
      "template": "1018",
      "type": "1",
      "x": "-110.5",
      "z": "-8.7109375",
      "y": "105.5",
      "roll": "0",
      "pitch": "0",
      "turn": "0",
      "id": "noname",
      "script": "DFtree2rialgate02.s"
    },
    {
      "template": "1018",
      "type": "1",
      "x": "-110.5",
      "z": "-8.7109375",
      "y": "102.5",
      "roll": "0",
      "pitch": "0",
      "turn": "0",
      "id": "noname",
      "script": "DFtree2rialgate02.s"
    },
    {
      "template": "1018",
      "type": "1",
      "x": "-110.5",
      "z": "-8.7109375",
      "y": "99.5",
      "roll": "0",
      "pitch": "0",
      "turn": "0",
      "id": "noname",
      "script": "DFtree2rialgate02.s"
    },
    {
      "template": "1018",
      "type": "1",
      "x": "-110.5",
      "z": "-8.7109375",
      "y": "96.5",
      "roll": "0",
      "pitch": "0",
      "turn": "0",
      "id": "noname",
      "script": "DFtree2rialgate02.s"
    },
    {
      "template": "1018",
      "type": "1",
      "x": "-110.5",
      "z": "-8.7109375",
      "y": "93.5",
      "roll": "0",
      "pitch": "0",
      "turn": "0",
      "id": "noname",
      "script": "DFtree2rialgate02.s"
    },
    {
      "template": "1018",
      "type": "1",
      "x": "-110.5",
      "z": "-8.7109375",
      "y": "90.5",
      "roll": "0",
      "pitch": "0",
      "turn": "0",
      "id": "noname",
      "script": "DFtree2rialgate02.s"
    },
    {
      "template": "254",
      "type": "2",
      "x": "-108.5",
      "z": "-9.125",
      "y": "117.5",
      "roll": "0",
      "pitch": "0",
      "turn": "0",
      "id": "noname",
      "script": "monsters\\Nubbed_Wormmouth.s"
    },
    {
      "template": "254",
      "type": "2",
      "x": "-114.5",
      "z": "-9.15625",
      "y": "121.5",
      "roll": "0",
      "pitch": "0",
      "turn": "0",
      "id": "noname",
      "script": "monsters\\Nubbed_Wormmouth.s"
    },
    {
      "template": "254",
      "type": "2",
      "x": "-120.5",
      "z": "-9.5",
      "y": "114.5",
      "roll": "0",
      "pitch": "0",
      "turn": "0",
      "id": "noname",
      "script": "monsters\\Nubbed_Wormmouth.s"
    },
    {
      "template": "1433",
      "type": "1",
      "x": "-122.5",
      "z": "1.75",
      "y": "2.5",
      "roll": "0",
      "pitch": "0",
      "turn": "0",
      "id": "noname",
      "script": "raiderroofbbed_Wormmouth.s"
    },
    {
      "template": "12",
      "type": "1",
      "x": "-45.5",
      "z": "-8.828125",
      "y": "85.5",
      "roll": "0",
      "pitch": "0",
      "turn": "0",
      "id": "noname",
      "script": "rockrroofbbed_Wormmouth.s"
    },
    {
      "template": "12",
      "type": "1",
      "x": "-56.5",
      "z": "-10",
      "y": "77.5",
      "roll": "0",
      "pitch": "0",
      "turn": "0",
      "id": "noname",
      "script": "rockrroofbbed_Wormmouth.s"
    },
    {
      "template": "12",
      "type": "1",
      "x": "-64.5",
      "z": "-9.53125",
      "y": "80.5",
      "roll": "0",
      "pitch": "0",
      "turn": "0",
      "id": "noname",
      "script": "rockrroofbbed_Wormmouth.s"
    },
    {
      "template": "12",
      "type": "1",
      "x": "-23.5",
      "z": "-9.21875",
      "y": "99.5",
      "roll": "0",
      "pitch": "0",
      "turn": "0",
      "id": "noname",
      "script": "rockrroofbbed_Wormmouth.s"
    },
    {
      "template": "12",
      "type": "1",
      "x": "-10.5",
      "z": "-8.421875",
      "y": "94.5",
      "roll": "0",
      "pitch": "10",
      "turn": "-5",
      "id": "noname",
      "script": "rockrroofbbed_Wormmouth.s"
    },
    {
      "template": "12",
      "type": "1",
      "x": "-7.5",
      "z": "-9.109375",
      "y": "79.5",
      "roll": "10",
      "pitch": "-10",
      "turn": "5",
      "id": "noname",
      "script": "rockrroofbbed_Wormmouth.s"
    },
    {
      "template": "12",
      "type": "1",
      "x": "-18.5",
      "z": "-8.8984375",
      "y": "70.5",
      "roll": "0",
      "pitch": "0",
      "turn": "0",
      "id": "noname",
      "script": "rockrroofbbed_Wormmouth.s"
    },
    {
      "template": "12",
      "type": "1",
      "x": "-28.5",
      "z": "-9.4140625",
      "y": "56.5",
      "roll": "0",
      "pitch": "0",
      "turn": "0",
      "id": "noname",
      "script": "rockrroofbbed_Wormmouth.s"
    },
    {
      "template": "12",
      "type": "1",
      "x": "-22.5",
      "z": "-9.4140625",
      "y": "48.5",
      "roll": "0",
      "pitch": "0",
      "turn": "0",
      "id": "noname",
      "script": "rockrroofbbed_Wormmouth.s"
    },
    {
      "template": "12",
      "type": "1",
      "x": "-24.5",
      "z": "-9.4140625",
      "y": "39.5",
      "roll": "0",
      "pitch": "0",
      "turn": "0",
      "id": "noname",
      "script": "rockrroofbbed_Wormmouth.s"
    },
    {
      "template": "12",
      "type": "1",
      "x": "-39.5",
      "z": "-8.8515625",
      "y": "42.5",
      "roll": "0",
      "pitch": "0",
      "turn": "0",
      "id": "noname",
      "script": "rockrroofbbed_Wormmouth.s"
    },
    {
      "template": "12",
      "type": "1",
      "x": "-22.5",
      "z": "-9.21875",
      "y": "23.5",
      "roll": "0",
      "pitch": "0",
      "turn": "-16.5",
      "id": "noname",
      "script": "rockrroofbbed_Wormmouth.s"
    },
    {
      "template": "12",
      "type": "1",
      "x": "-30.5",
      "z": "-9.4375",
      "y": "11.5",
      "roll": "0",
      "pitch": "0",
      "turn": "0",
      "id": "noname",
      "script": "rockrroofbbed_Wormmouth.s"
    },
    {
      "template": "12",
      "type": "1",
      "x": "-40.5",
      "z": "-10",
      "y": "27.5",
      "roll": "0",
      "pitch": "0",
      "turn": "0",
      "id": "noname",
      "script": "rockrroofbbed_Wormmouth.s"
    },
    {
      "template": "12",
      "type": "1",
      "x": "-57.5",
      "z": "-9.109375",
      "y": "27.5",
      "roll": "0",
      "pitch": "0",
      "turn": "0",
      "id": "noname",
      "script": "rockrroofbbed_Wormmouth.s"
    },
    {
      "template": "12",
      "type": "1",
      "x": "-58.5",
      "z": "-9.8515625",
      "y": "9.890625",
      "roll": "-10",
      "pitch": "0",
      "turn": "-5",
      "id": "noname",
      "script": "rockrroofbbed_Wormmouth.s"
    },
    {
      "template": "12",
      "type": "1",
      "x": "-69.5",
      "z": "-9.21875",
      "y": "46.5",
      "roll": "0",
      "pitch": "0",
      "turn": "0",
      "id": "noname",
      "script": "rockrroofbbed_Wormmouth.s"
    },
    {
      "template": "12",
      "type": "1",
      "x": "-60.5",
      "z": "-8.5390625",
      "y": "62.5",
      "roll": "0",
      "pitch": "-15",
      "turn": "0",
      "id": "noname",
      "script": "rockrroofbbed_Wormmouth.s"
    },
    {
      "template": "12",
      "type": "1",
      "x": "-83.5",
      "z": "-9.3359375",
      "y": "59.5",
      "roll": "0",
      "pitch": "0",
      "turn": "0",
      "id": "noname",
      "script": "rockrroofbbed_Wormmouth.s"
    },
    {
      "template": "12",
      "type": "1",
      "x": "-117.5",
      "z": "-9.21875",
      "y": "36.5",
      "roll": "0",
      "pitch": "0",
      "turn": "0",
      "id": "noname",
      "script": "rockrroofbbed_Wormmouth.s"
    },
    {
      "template": "12",
      "type": "1",
      "x": "-88.5",
      "z": "-11.125",
      "y": "8.5",
      "roll": "0",
      "pitch": "0",
      "turn": "0",
      "id": "noname",
      "script": "rockrroofbbed_Wormmouth.s"
    },
    {
      "template": "12",
      "type": "1",
      "x": "-87.890625",
      "z": "-9.65625",
      "y": "20.5",
      "roll": "10",
      "pitch": "-5",
      "turn": "-28.5",
      "id": "noname",
      "script": "rockrroofbbed_Wormmouth.s"
    },
    {
      "template": "12",
      "type": "1",
      "x": "-75.5",
      "z": "-10",
      "y": "66.5",
      "roll": "0",
      "pitch": "0",
      "turn": "0",
      "id": "noname",
      "script": "rockrroofbbed_Wormmouth.s"
    },
    {
      "template": "12",
      "type": "1",
      "x": "-105.5",
      "z": "-9.125",
      "y": "81.5",
      "roll": "0",
      "pitch": "0",
      "turn": "0",
      "id": "noname",
      "script": "rockrroofbbed_Wormmouth.s"
    },
    {
      "template": "12",
      "type": "1",
      "x": "-116.5",
      "z": "-9.21875",
      "y": "81.5",
      "roll": "0",
      "pitch": "0",
      "turn": "0",
      "id": "noname",
      "script": "rockrroofbbed_Wormmouth.s"
    },
    {
      "template": "12",
      "type": "1",
      "x": "-71.5",
      "z": "-9.4921875",
      "y": "99.5",
      "roll": "0",
      "pitch": "0",
      "turn": "0",
      "id": "noname",
      "script": "rockrroofbbed_Wormmouth.s"
    },
    {
      "template": "12",
      "type": "1",
      "x": "-94.5",
      "z": "-10",
      "y": "101.5",
      "roll": "0",
      "pitch": "0",
      "turn": "0",
      "id": "noname",
      "script": "rockrroofbbed_Wormmouth.s"
    },
    {
      "template": "12",
      "type": "1",
      "x": "-119.5",
      "z": "-10",
      "y": "104.5",
      "roll": "0",
      "pitch": "0",
      "turn": "0",
      "id": "noname",
      "script": "rockrroofbbed_Wormmouth.s"
    },
    {
      "template": "12",
      "type": "1",
      "x": "-95.5",
      "z": "-9.75",
      "y": "120.5",
      "roll": "0",
      "pitch": "0",
      "turn": "0",
      "id": "noname",
      "script": "rockrroofbbed_Wormmouth.s"
    },
    {
      "template": "6",
      "type": "1",
      "x": "-77.28125",
      "z": "-10.53125",
      "y": "8.5",
      "roll": "0",
      "pitch": "0",
      "turn": "0",
      "id": "noname",
      "script": "barreloofbbed_Wormmouth.s"
    },
    {
      "template": "6",
      "type": "1",
      "x": "-83.5",
      "z": "-10.390625",
      "y": "11.5",
      "roll": "0",
      "pitch": "0",
      "turn": "0",
      "id": "noname",
      "script": "barreloofbbed_Wormmouth.s"
    },
    {
      "template": "6",
      "type": "1",
      "x": "-86.5",
      "z": "-10.3125",
      "y": "17.5",
      "roll": "0",
      "pitch": "0",
      "turn": "0",
      "id": "noname",
      "script": "barreloofbbed_Wormmouth.s"
    },
    {
      "template": "6",
      "type": "1",
      "x": "-85.5",
      "z": "-10.140625",
      "y": "19.5",
      "roll": "0",
      "pitch": "0",
      "turn": "0",
      "id": "noname",
      "script": "barreloofbbed_Wormmouth.s"
    },
    {
      "template": "6",
      "type": "1",
      "x": "-85.5",
      "z": "-10.65625",
      "y": "17.5",
      "roll": "0",
      "pitch": "0",
      "turn": "0",
      "id": "noname",
      "script": "barreloofbbed_Wormmouth.s"
    },
    {
      "template": "6",
      "type": "1",
      "x": "-86.5",
      "z": "-10.796875",
      "y": "12.5",
      "roll": "0",
      "pitch": "0",
      "turn": "0",
      "id": "noname",
      "script": "barreloofbbed_Wormmouth.s"
    },
    {
      "template": "76",
      "type": "1",
      "x": "-76.671875",
      "z": "-10.828125",
      "y": "17.5",
      "roll": "0",
      "pitch": "0",
      "turn": "0",
      "id": "noname",
      "script": "crateoofbbed_Wormmouth.s"
    },
    {
      "template": "76",
      "type": "1",
      "x": "-75.5",
      "z": "-10.921875",
      "y": "15.5",
      "roll": "0",
      "pitch": "0",
      "turn": "0",
      "id": "noname",
      "script": "crateoofbbed_Wormmouth.s"
    },
    {
      "template": "76",
      "type": "1",
      "x": "-84.65625",
      "z": "-10.2890625",
      "y": "8.5",
      "roll": "0",
      "pitch": "0",
      "turn": "0",
      "id": "noname",
      "script": "crateoofbbed_Wormmouth.s"
    },
    {
      "template": "76",
      "type": "1",
      "x": "-85.28125",
      "z": "-10.296875",
      "y": "10.015625",
      "roll": "0",
      "pitch": "0",
      "turn": "0",
      "id": "noname",
      "script": "crateoofbbed_Wormmouth.s"
    },
    {
      "template": "87",
      "type": "1",
      "x": "-67.015625",
      "z": "-10.390625",
      "y": "117.5",
      "roll": "0",
      "pitch": "0",
      "turn": "-90",
      "id": "noname",
      "script": "tradinggatebed_Wormmouth.s"
    },
    {
      "template": "87",
      "type": "1",
      "x": "-75.2421875",
      "z": "-10.6484375",
      "y": "110.5",
      "roll": "0",
      "pitch": "0",
      "turn": "-85",
      "id": "noname",
      "script": "tradinggatebed_Wormmouth.s"
    },
    {
      "template": "87",
      "type": "1",
      "x": "-75.6171875",
      "z": "-10.2734375",
      "y": "95.5",
      "roll": "0",
      "pitch": "0",
      "turn": "-60",
      "id": "noname",
      "script": "tradinggatebed_Wormmouth.s"
    },
    {
      "template": "87",
      "type": "1",
      "x": "-71.0703125",
      "z": "-10.53125",
      "y": "79.5",
      "roll": "0",
      "pitch": "0",
      "turn": "-70",
      "id": "noname",
      "script": "tradinggatebed_Wormmouth.s"
    },
    {
      "template": "87",
      "type": "1",
      "x": "-79.34375",
      "z": "-10.28125",
      "y": "67.5234375",
      "roll": "0",
      "pitch": "0",
      "turn": "40",
      "id": "noname",
      "script": "tradinggatebed_Wormmouth.s"
    },
    {
      "template": "87",
      "type": "1",
      "x": "-92.5",
      "z": "-10.546875",
      "y": "63.890625",
      "roll": "0",
      "pitch": "0",
      "turn": "0",
      "id": "noname",
      "script": "tradinggatebed_Wormmouth.s"
    },
    {
      "template": "87",
      "type": "1",
      "x": "-106.5",
      "z": "-10.875",
      "y": "64.109375",
      "roll": "0",
      "pitch": "0",
      "turn": "0",
      "id": "noname",
      "script": "tradinggatebed_Wormmouth.s"
    },
    {
      "template": "87",
      "type": "1",
      "x": "-64.2265625",
      "z": "-10.15625",
      "y": "123.9375",
      "roll": "0",
      "pitch": "0",
      "turn": "-60",
      "id": "noname",
      "script": "tradinggatebed_Wormmouth.s"
    },
    {
      "template": "1",
      "type": "1",
      "x": "-8.5",
      "z": "-9.5625",
      "y": "22.5",
      "roll": "0",
      "pitch": "0",
      "turn": "70",
      "id": "noname",
      "script": "EMPTY_CHESTbed_Wormmouth.s"
    },
    {
      "template": "1",
      "type": "1",
      "x": "-8.5",
      "z": "-9.5625",
      "y": "22.5",
      "roll": "0",
      "pitch": "0",
      "turn": "70",
      "id": "noname",
      "script": "!EMPTY_CHESTed_Wormmouth.s"
    },
    {
      "template": "272",
      "type": "2",
      "x": "-20.5",
      "z": "-8.6875",
      "y": "118.5",
      "roll": "0",
      "pitch": "0",
      "turn": "0",
      "id": "twight",
      "script": "monsters\\Tunnel_Wight.s"
    }
  ]
}
